data_preprocessing_lib/__init__.py
data_preprocessing_lib/categorical_encoder.py
data_preprocessing_lib/data_type_converter.py
data_preprocessing_lib/datetime_handler.py
data_preprocessing_lib/missing_value_handler.py
data_preprocessing_lib/outlier_handler.py
data_preprocessing_lib/scaler.py
data_preprocessing_lib/text_cleaner.py
oguzhan_gokcekoca-0.1.0.dist-info/METADATA
oguzhan_gokcekoca-0.1.0.dist-info/WHEEL
oguzhan_gokcekoca-0.1.0.dist-info/top_level.txt
oguzhan_gokcekoca-0.1.0.dist-info/RECORD
